odoo/addons/l10n_it_fatturapa/README.rst
odoo/addons/l10n_it_fatturapa/__init__.py
odoo/addons/l10n_it_fatturapa/__manifest__.py
odoo/addons/l10n_it_fatturapa/bindings/__init__.py
odoo/addons/l10n_it_fatturapa/bindings/_ds.py
odoo/addons/l10n_it_fatturapa/bindings/fatturapa_v_1_2.py
odoo/addons/l10n_it_fatturapa/controllers/__init__.py
odoo/addons/l10n_it_fatturapa/controllers/main.py
odoo/addons/l10n_it_fatturapa/data/FoglioStileAssoSoftware_v1.1.xsl
odoo/addons/l10n_it_fatturapa/data/fatturaordinaria_v1.2.1.xsl
odoo/addons/l10n_it_fatturapa/data/fatturapa_data.xml
odoo/addons/l10n_it_fatturapa/data/welfare.fund.type.csv
odoo/addons/l10n_it_fatturapa/demo/account_invoice_fatturapa.xml
odoo/addons/l10n_it_fatturapa/i18n/am.po
odoo/addons/l10n_it_fatturapa/i18n/ar.po
odoo/addons/l10n_it_fatturapa/i18n/bg.po
odoo/addons/l10n_it_fatturapa/i18n/bs.po
odoo/addons/l10n_it_fatturapa/i18n/ca.po
odoo/addons/l10n_it_fatturapa/i18n/cs.po
odoo/addons/l10n_it_fatturapa/i18n/da.po
odoo/addons/l10n_it_fatturapa/i18n/de.po
odoo/addons/l10n_it_fatturapa/i18n/el_GR.po
odoo/addons/l10n_it_fatturapa/i18n/en_GB.po
odoo/addons/l10n_it_fatturapa/i18n/es.po
odoo/addons/l10n_it_fatturapa/i18n/es_AR.po
odoo/addons/l10n_it_fatturapa/i18n/es_CL.po
odoo/addons/l10n_it_fatturapa/i18n/es_CO.po
odoo/addons/l10n_it_fatturapa/i18n/es_CR.po
odoo/addons/l10n_it_fatturapa/i18n/es_DO.po
odoo/addons/l10n_it_fatturapa/i18n/es_EC.po
odoo/addons/l10n_it_fatturapa/i18n/es_ES.po
odoo/addons/l10n_it_fatturapa/i18n/es_MX.po
odoo/addons/l10n_it_fatturapa/i18n/es_PE.po
odoo/addons/l10n_it_fatturapa/i18n/es_PY.po
odoo/addons/l10n_it_fatturapa/i18n/es_VE.po
odoo/addons/l10n_it_fatturapa/i18n/et.po
odoo/addons/l10n_it_fatturapa/i18n/eu.po
odoo/addons/l10n_it_fatturapa/i18n/fa.po
odoo/addons/l10n_it_fatturapa/i18n/fi.po
odoo/addons/l10n_it_fatturapa/i18n/fr.po
odoo/addons/l10n_it_fatturapa/i18n/fr_CA.po
odoo/addons/l10n_it_fatturapa/i18n/fr_CH.po
odoo/addons/l10n_it_fatturapa/i18n/fr_FR.po
odoo11_addon_l10n_it_fatturapa-11.0.1.1.0.dist-info/METADATA
odoo11_addon_l10n_it_fatturapa-11.0.1.1.0.dist-info/WHEEL
odoo11_addon_l10n_it_fatturapa-11.0.1.1.0.dist-info/top_level.txt
odoo11_addon_l10n_it_fatturapa-11.0.1.1.0.dist-info/RECORD
