Metadata-Version: 2.1
Name: odoo11-addon-l10n-it-fatturapa
Version: 11.0.1.1.0
Summary: Electronic invoices
Home-page: https://github.com/OCA/l10n-italy/
Author: Davide Corio, Agile Business Group, Innoviu, Odoo Italia Network, Odoo Community Association (OCA)
Author-email: support@odoo-community.org
License: LGPL-3
Platform: UNKNOWN
Classifier: Programming Language :: Python
Classifier: Framework :: Odoo
Classifier: License :: OSI Approved :: GNU Lesser General Public License v3 (LGPLv3)
Requires-Python: >=2.7, !=3.0.*, !=3.1.*, !=3.2.*, !=3.3.*, !=3.4.*
Requires-Dist: PyXB (==1.2.5)
Requires-Dist: asn1crypto
Requires-Dist: odoo11-addon-l10n-it-account
Requires-Dist: odoo11-addon-l10n-it-account-tax-kind
Requires-Dist: odoo11-addon-l10n-it-esigibilita-iva
Requires-Dist: odoo11-addon-l10n-it-fiscal-document-type
Requires-Dist: odoo11-addon-l10n-it-fiscal-payment-term
Requires-Dist: odoo11-addon-l10n-it-fiscalcode
Requires-Dist: odoo11-addon-l10n-it-ipa
Requires-Dist: odoo11-addon-l10n-it-rea
Requires-Dist: odoo11-addon-l10n-it-split-payment
Requires-Dist: odoo11-addon-partner-firstname
Requires-Dist: odoo (<11.1dev,>=11.0a)
